Funcoes_matematicas/__init__.py
Funcoes_matematicas/processamento/__init__.py
Funcoes_matematicas/processamento/calculo_area.py
Funcoes_matematicas/processamento/geracao_pontos.py
Funcoes_matematicas/utils/__init__.py
Funcoes_matematicas/utils/plot_pontos.py
Funcoes_matematicas-0.0.2.dist-info/METADATA
Funcoes_matematicas-0.0.2.dist-info/WHEEL
Funcoes_matematicas-0.0.2.dist-info/top_level.txt
Funcoes_matematicas-0.0.2.dist-info/RECORD
