Metadata-Version: 2.1
Name: Funcoes-matematicas
Version: 0.0.2
Summary: Plotagem de funções matemáticas simples
Home-page: https://github.com/carlosfalcone/PacotesPython
Author: Carlos_Falcone
Author-email: carloseduardo.falcone@gmail.com
Requires-Python: >=3.5
Requires-Dist: matplotlib
